m2_runAudioExperiment-0.9.0-py3.7-nspkg.pth
m2/runAudioExperiment/__init__.py
m2/runAudioExperiment/audio.py
m2/runAudioExperiment/cli.py
m2/runAudioExperiment/env.py
m2/runAudioExperiment/experiment_config.py
m2/runAudioExperiment/trial_data.py
m2_runAudioExperiment-0.9.0.dist-info/LICENSE
m2_runAudioExperiment-0.9.0.dist-info/METADATA
m2_runAudioExperiment-0.9.0.dist-info/WHEEL
m2_runAudioExperiment-0.9.0.dist-info/entry_points.txt
m2_runAudioExperiment-0.9.0.dist-info/namespace_packages.txt
m2_runAudioExperiment-0.9.0.dist-info/top_level.txt
m2_runAudioExperiment-0.9.0.dist-info/RECORD
