Metadata-Version: 2.1
Name: m2-runAudioExperiment
Version: 0.9.0
Summary: Library and utility to run an tapping audio experiment. From "Simple and cheap setup for measuring timed responses to auditory stimuli" (Miguel et. al., under review).
Home-page: https://github.com/m2march/runAudioExperiment
Author: Martin "March" Miguel
Author-email: m2.march@gmail.com
License: MIT
Platform: UNKNOWN
Requires-Dist: psychopy
Requires-Dist: pydub
Requires-Dist: numpy
Requires-Dist: sounddevice
Requires-Dist: fuzzywuzzy
Requires-Dist: pyyaml
Requires-Dist: pandas
Requires-Dist: scipy
